LICENSE
MANIFEST.in
README.md
branca.py
setup.cfg
setup.py
xchacha20poly1305.py
pybranca.egg-info/PKG-INFO
pybranca.egg-info/SOURCES.txt
pybranca.egg-info/dependency_links.txt
pybranca.egg-info/requires.txt
pybranca.egg-info/top_level.txt