Metadata-Version: 2.1
Name: pybranca
Version: 0.5.0
Summary: Authenticated and encrypted API tokens using modern crypto
Home-page: https://github.com/tuupola/pybranca
Author: Mika Tuupola
Author-email: tuupola@appelsiini.net
Maintainer: Mika Tuupola
Maintainer-email: tuupola@appelsiini.net
License: MIT
Keywords: api,token,jwt,xchacha20,poly1305
Platform: UNKNOWN
Classifier: Development Status :: 4 - Beta
Classifier: Programming Language :: Python
Classifier: Topic :: Security
Classifier: License :: OSI Approved :: MIT License
